pywise_pkg/__init__.py
pywise_pkg/cli.py
pywise_pkg/core/__init__.py
pywise_pkg/core/detector.py
pywise_pkg/core/docker_gen.py
pywise_pkg/core/migrator.py
pywise_pkg/core/resolver.py
pywise_pkg/utils/__init__.py
pywise_pkg/utils/helpers.py
tests/__init__.py
tests/test_advanced.py
pywise_pkg-0.2.0.dist-info/LICENSE
pywise_pkg-0.2.0.dist-info/METADATA
pywise_pkg-0.2.0.dist-info/WHEEL
pywise_pkg-0.2.0.dist-info/entry_points.txt
pywise_pkg-0.2.0.dist-info/top_level.txt
pywise_pkg-0.2.0.dist-info/RECORD
