Metadata-Version: 2.1
Name: pywise-pkg
Version: 0.2.0
Summary: Intelligent Python dependency management with conda-pip hybrid support
Home-page: https://github.com/shreyjain26/pywise_pkg
Author: pywise_pkg Contributors
Author-email: shreyjain026@gmail.com
License: UNKNOWN
Platform: UNKNOWN
Classifier: Development Status :: 4 - Beta
Classifier: Intended Audience :: Developers
Classifier: License :: OSI Approved :: MIT License
Classifier: Operating System :: OS Independent
Classifier: Programming Language :: Python :: 3
Classifier: Programming Language :: Python :: 3.8
Classifier: Programming Language :: Python :: 3.9
Classifier: Programming Language :: Python :: 3.10
Classifier: Programming Language :: Python :: 3.11
Classifier: Programming Language :: Python :: 3.12
Classifier: Topic :: Software Development :: Libraries :: Python Modules
Classifier: Topic :: System :: Systems Administration
Requires-Python: >=3.8
License-File: LICENSE
Requires-Dist: click (>=8.0.0)
Requires-Dist: networkx (>=2.8.0)
Requires-Dist: packaging (>=21.0)
Requires-Dist: pyyaml (>=6.0)
Requires-Dist: requests (>=2.25.0)
Requires-Dist: rich (>=12.0.0)
Requires-Dist: toml (>=0.10.0)
Requires-Dist: importlib-metadata (>=4.0.0) ; python_version < "3.10"
